{
  "month": "2026-01-01",
  "source_uri": "file:///data/monthly_account_status.parquet",
  "rows_scanned": 10587,
  "duplicates_found": 308,
  "total_alerts": 141,
  "arr_threshold": 10000,
  "alerts": [
    {
      "account_id": "a00636",
      "account_name": "Account 0636",
      "account_region": "EMEA",
      "arr": 10211,
      "duration_months": 2,
      "risk_start_month": "2025-12-01",
      "renewal_date": "2026-06-01",
      "account_owner": "owner36@example.com",
      "channel": "emea-risk-alerts",
      "routable": true
    },
    {
      "account_id": "a00090",
      "account_name": "Account 0090",
      "account_region": null,
      "arr": 49917,
      "duration_months": 2,
      "risk_start_month": "2025-12-01",
      "renewal_date": null,
      "account_owner": "owner40@example.com",
      "channel": null,
      "routable": false
    }
  ]
}